aidial_adapter_anthropic/_utils/json.py
aidial_adapter_anthropic/_utils/list.py
aidial_adapter_anthropic/_utils/pydantic.py
aidial_adapter_anthropic/_utils/resource.py
aidial_adapter_anthropic/_utils/text.py
aidial_adapter_anthropic/adapter/__init__.py
aidial_adapter_anthropic/adapter/_base.py
aidial_adapter_anthropic/adapter/_claude/adapter.py
aidial_adapter_anthropic/adapter/_claude/blocks.py
aidial_adapter_anthropic/adapter/_claude/citations.py
aidial_adapter_anthropic/adapter/_claude/config.py
aidial_adapter_anthropic/adapter/_claude/converters.py
aidial_adapter_anthropic/adapter/_claude/params.py
aidial_adapter_anthropic/adapter/_claude/state.py
aidial_adapter_anthropic/adapter/_claude/tokenizer/__init__.py
aidial_adapter_anthropic/adapter/_claude/tokenizer/anthropic.py
aidial_adapter_anthropic/adapter/_claude/tokenizer/approximate.py
aidial_adapter_anthropic/adapter/_claude/tokenizer/base.py
aidial_adapter_anthropic/adapter/_claude/tools.py
aidial_adapter_anthropic/adapter/_decorator/base.py
aidial_adapter_anthropic/adapter/_decorator/preprocess.py
aidial_adapter_anthropic/adapter/_decorator/replicator.py
aidial_adapter_anthropic/adapter/_errors.py
aidial_adapter_anthropic/adapter/_tokenize.py
aidial_adapter_anthropic/adapter/_truncate_prompt.py
aidial_adapter_anthropic/adapter/claude.py
aidial_adapter_anthropic/dial/_attachments.py
aidial_adapter_anthropic/dial/_lazy_stage.py
aidial_adapter_anthropic/dial/_message.py
aidial_adapter_anthropic/dial/consumer.py
aidial_adapter_anthropic/dial/request.py
aidial_adapter_anthropic/dial/resource.py
aidial_adapter_anthropic/dial/storage.py
aidial_adapter_anthropic/dial/token_usage.py
aidial_adapter_anthropic/dial/tools.py
aidial_adapter_anthropic-0.1.0.dist-info/LICENSE
aidial_adapter_anthropic-0.1.0.dist-info/METADATA
aidial_adapter_anthropic-0.1.0.dist-info/WHEEL
aidial_adapter_anthropic-0.1.0.dist-info/RECORD
