Metadata-Version: 2.3
Name: aidial-adapter-anthropic
Version: 0.1.0
Summary: Package implementing adapter from DIAL Chat Completions API to Anthropic API
License: Apache-2.0
Keywords: ai
Author: EPAM RAIL
Author-email: SpecialEPM-DIALDevTeam@epam.com
Requires-Python: >=3.11,<4.0
Classifier: Topic :: Software Development :: Libraries :: Python Modules
Requires-Dist: aidial-sdk (>=0.28.0,<1)
Requires-Dist: aiohttp (>=3.13.3,<4)
Requires-Dist: anthropic (>=0.75.0,<1)
Requires-Dist: pillow (>=10.4.0,<11)
Requires-Dist: pydantic (>=1.10.17,<3)
Project-URL: Documentation, https://epam-rail.com/dial_api
Project-URL: Homepage, https://epam-rail.com
Project-URL: Repository, https://github.com/epam/ai-dial-adapter-anthropic/
